fancy_utils/__init__.py
fancy_utils/array_utils.py
fancy_utils/string_utils.py
tests/__init__.py
tests/test_array_utils.py
tests/test_string_utils.py
fancy_utils_pawel-0.1.dist-info/LICENSE
fancy_utils_pawel-0.1.dist-info/METADATA
fancy_utils_pawel-0.1.dist-info/WHEEL
fancy_utils_pawel-0.1.dist-info/top_level.txt
fancy_utils_pawel-0.1.dist-info/RECORD
